Metadata-Version: 1.0
Name: cloudshell-networking-huawei-vrp
Version: 2.0.0
Summary: QualiSystems networking huawei VRP specific Package
Home-page: http://www.qualisystems.com/
Author: QualiSystems
Author-email: info@qualisystems.com
License: UNKNOWN
Platform: UNKNOWN
